[
  {
    "symbol": "ABBV",
    "strike": 200.0,
    "expiry": "2026-05-15",
    "contracts": 5000,
    "current_premium": 4.08,
    "original_premium": 4.08,
    "trade_date": "2026-02-19"
  },
  {
    "symbol": "AMD",
    "strike": 195.0,
    "expiry": "2026-03-06",
    "contracts": 1200,
    "current_premium": 3.25,
    "original_premium": 3.25,
    "trade_date": "2026-02-19"
  },
  {
    "symbol": "ANET",
    "strike": 105.0,
    "expiry": "2026-04-17",
    "contracts": 8000,
    "current_premium": 1.54,
    "original_premium": 1.54,
    "trade_date": "2026-02-19"
  },
  {
    "symbol": "APP",
    "strike": 360.0,
    "expiry": "2026-09-18",
    "contracts": 400,
    "current_premium": 56.35,
    "original_premium": 56.35,
    "trade_date": "2026-02-19"
  },
  {
    "symbol": "ASTS",
    "strike": 79.0,
    "expiry": "2026-02-27",
    "contracts": 1200,
    "current_premium": 0.29,
    "original_premium": 0.29,
    "trade_date": "2026-02-19"
  },
  {
    "symbol": "BAC",
    "strike": 35.0,
    "expiry": "2028-12-15",
    "contracts": 1500,
    "current_premium": 2.73,
    "original_premium": 2.73,
    "trade_date": "2026-02-19"
  },
  {
    "symbol": "CDNS",
    "strike": 245.0,
    "expiry": "2026-03-20",
    "contracts": 3900,
    "current_premium": 0.85,
    "original_premium": 0.85,
    "trade_date": "2026-02-19"
  },
  {
    "symbol": "CL",
    "strike": 90.0,
    "expiry": "2026-03-20",
    "contracts": 7000,
    "current_premium": 0.28,
    "original_premium": 0.28,
    "trade_date": "2026-02-19"
  },
  {
    "symbol": "CRH",
    "strike": 105.0,
    "expiry": "2026-03-20",
    "contracts": 1050,
    "current_premium": 0.65,
    "original_premium": 0.65,
    "trade_date": "2026-02-19"
  },
  {
    "symbol": "CRL",
    "strike": 140.0,
    "expiry": "2026-12-18",
    "contracts": 1020,
    "current_premium": 10.85,
    "original_premium": 10.85,
    "trade_date": "2026-02-19"
  },
  {
    "symbol": "CRWV",
    "strike": 37.5,
    "expiry": "2026-04-17",
    "contracts": 27200,
    "current_premium": 0.38,
    "original_premium": 0.38,
    "trade_date": "2026-02-19"
  },
  {
    "symbol": "DUOL",
    "strike": 105.0,
    "expiry": "2026-09-18",
    "contracts": 800,
    "current_premium": 21.95,
    "original_premium": 21.95,
    "trade_date": "2026-02-19"
  },
  {
    "symbol": "EQT",
    "strike": 50.0,
    "expiry": "2026-03-20",
    "contracts": 34400,
    "current_premium": 0.13,
    "original_premium": 0.13,
    "trade_date": "2026-02-19"
  },
  {
    "symbol": "EXE",
    "strike": 90.0,
    "expiry": "2026-03-20",
    "contracts": 7500,
    "current_premium": 0.32,
    "original_premium": 0.32,
    "trade_date": "2026-02-19"
  },
  {
    "symbol": "FCX",
    "strike": 60.0,
    "expiry": "2026-09-18",
    "contracts": 1775,
    "current_premium": 5.42,
    "original_premium": 5.42,
    "trade_date": "2026-02-19"
  },
  {
    "symbol": "FRO",
    "strike": 23.0,
    "expiry": "2026-08-21",
    "contracts": 1700,
    "current_premium": 0.9,
    "original_premium": 0.9,
    "trade_date": "2026-02-19"
  },
  {
    "symbol": "GLD",
    "strike": 370.0,
    "expiry": "2026-03-20",
    "contracts": 18500,
    "current_premium": 0.3,
    "original_premium": 0.3,
    "trade_date": "2026-02-19"
  },
  {
    "symbol": "HAL",
    "strike": 30.0,
    "expiry": "2026-04-17",
    "contracts": 3000,
    "current_premium": 0.36,
    "original_premium": 0.36,
    "trade_date": "2026-02-19"
  },
  {
    "symbol": "ILMN",
    "strike": 110.0,
    "expiry": "2026-03-20",
    "contracts": 1000,
    "current_premium": 1.42,
    "original_premium": 1.42,
    "trade_date": "2026-02-19"
  },
  {
    "symbol": "INTC",
    "strike": 42.0,
    "expiry": "2026-09-18",
    "contracts": 2900,
    "current_premium": 5.85,
    "original_premium": 5.85,
    "trade_date": "2026-02-19"
  },
  {
    "symbol": "INTC",
    "strike": 42.0,
    "expiry": "2026-12-18",
    "contracts": 3000,
    "current_premium": 0.0,
    "original_premium": null,
    "trade_date": "2026-02-19"
  },
  {
    "symbol": "INTC",
    "strike": 30.0,
    "expiry": "2027-01-15",
    "contracts": 1000,
    "current_premium": 2.55,
    "original_premium": 2.55,
    "trade_date": "2026-02-19"
  },
  {
    "symbol": "IREN",
    "strike": 33.0,
    "expiry": "2026-03-06",
    "contracts": 1500,
    "current_premium": 0.33,
    "original_premium": 0.33,
    "trade_date": "2026-02-19"
  },
  {
    "symbol": "KKR",
    "strike": 80.0,
    "expiry": "2027-01-15",
    "contracts": 600,
    "current_premium": 8.85,
    "original_premium": 8.85,
    "trade_date": "2026-02-19"
  },
  {
    "symbol": "KTOS",
    "strike": 65.0,
    "expiry": "2026-05-15",
    "contracts": 2000,
    "current_premium": 3.12,
    "original_premium": 3.12,
    "trade_date": "2026-02-19"
  },
  {
    "symbol": "LITE",
    "strike": 590.0,
    "expiry": "2026-02-27",
    "contracts": 1000,
    "current_premium": 0.5,
    "original_premium": 0.5,
    "trade_date": "2026-02-19"
  },
  {
    "symbol": "LLY",
    "strike": 895.0,
    "expiry": "2026-03-27",
    "contracts": 1050,
    "current_premium": 5.5,
    "original_premium": 5.5,
    "trade_date": "2026-02-19"
  },
  {
    "symbol": "MRVL",
    "strike": 80.0,
    "expiry": "2026-03-06",
    "contracts": 1050,
    "current_premium": 5.03,
    "original_premium": 5.03,
    "trade_date": "2026-02-19"
  },
  {
    "symbol": "NFLX",
    "strike": 62.0,
    "expiry": "2028-01-21",
    "contracts": 600,
    "current_premium": 7.0,
    "original_premium": 7.0,
    "trade_date": "2026-02-19"
  },
  {
    "symbol": "PANW",
    "strike": 130.0,
    "expiry": "2026-07-17",
    "contracts": 750,
    "current_premium": 6.25,
    "original_premium": 6.25,
    "trade_date": "2026-02-19"
  },
  {
    "symbol": "PLTR",
    "strike": 128.0,
    "expiry": "2026-02-27",
    "contracts": 5400,
    "current_premium": 0.12,
    "original_premium": 0.12,
    "trade_date": "2026-02-19"
  },
  {
    "symbol": "PZZA",
    "strike": 27.5,
    "expiry": "2026-04-17",
    "contracts": 5600,
    "current_premium": 0.62,
    "original_premium": 0.62,
    "trade_date": "2026-02-19"
  },
  {
    "symbol": "RIO",
    "strike": 90.0,
    "expiry": "2026-03-20",
    "contracts": 1400,
    "current_premium": 0.98,
    "original_premium": 0.98,
    "trade_date": "2026-02-19"
  },
  {
    "symbol": "RIVN",
    "strike": 19.0,
    "expiry": "2026-05-15",
    "contracts": 3000,
    "current_premium": 4.25,
    "original_premium": 4.25,
    "trade_date": "2026-02-19"
  },
  {
    "symbol": "RKT",
    "strike": 18.0,
    "expiry": "2026-02-27",
    "contracts": 1000,
    "current_premium": 0.98,
    "original_premium": 0.98,
    "trade_date": "2026-02-19"
  },
  {
    "symbol": "RXT",
    "strike": 1.0,
    "expiry": "2026-08-21",
    "contracts": 3000,
    "current_premium": 0.25,
    "original_premium": 0.25,
    "trade_date": "2026-02-19"
  },
  {
    "symbol": "SA",
    "strike": 30.0,
    "expiry": "2026-05-15",
    "contracts": 1350,
    "current_premium": 1.73,
    "original_premium": 1.73,
    "trade_date": "2026-02-19"
  },
  {
    "symbol": "STX",
    "strike": 400.0,
    "expiry": "2026-03-20",
    "contracts": 1000,
    "current_premium": 23.8,
    "original_premium": 23.8,
    "trade_date": "2026-02-19"
  },
  {
    "symbol": "T",
    "strike": 18.0,
    "expiry": "2028-01-21",
    "contracts": 1000,
    "current_premium": 0.66,
    "original_premium": 0.66,
    "trade_date": "2026-02-19"
  },
  {
    "symbol": "TGT",
    "strike": 115.0,
    "expiry": "2026-04-17",
    "contracts": 1350,
    "current_premium": 7.05,
    "original_premium": 7.05,
    "trade_date": "2026-02-19"
  },
  {
    "symbol": "TTD",
    "strike": 25.0,
    "expiry": "2026-09-18",
    "contracts": 2000,
    "current_premium": 5.2,
    "original_premium": 5.2,
    "trade_date": "2026-02-19"
  },
  {
    "symbol": "UBER",
    "strike": 50.0,
    "expiry": "2026-08-21",
    "contracts": 2000,
    "current_premium": 1.06,
    "original_premium": 1.06,
    "trade_date": "2026-02-19"
  },
  {
    "symbol": "USO",
    "strike": 75.0,
    "expiry": "2026-04-17",
    "contracts": 3000,
    "current_premium": 3.5,
    "original_premium": 3.5,
    "trade_date": "2026-02-19"
  },
  {
    "symbol": "VNET",
    "strike": 11.0,
    "expiry": "2026-03-20",
    "contracts": 4000,
    "current_premium": 0.93,
    "original_premium": 0.93,
    "trade_date": "2026-02-19"
  },
  {
    "symbol": "VST",
    "strike": 100.0,
    "expiry": "2026-03-20",
    "contracts": 8000,
    "current_premium": 0.33,
    "original_premium": 0.33,
    "trade_date": "2026-02-19"
  },
  {
    "symbol": "WMT",
    "strike": 113.0,
    "expiry": "2026-03-13",
    "contracts": 8100,
    "current_premium": 0.36,
    "original_premium": 0.36,
    "trade_date": "2026-02-19"
  },
  {
    "symbol": "Z",
    "strike": 40.0,
    "expiry": "2026-03-20",
    "contracts": 1000,
    "current_premium": 0.53,
    "original_premium": 0.53,
    "trade_date": "2026-02-19"
  },
  {
    "symbol": "AAOI",
    "strike": 35.0,
    "expiry": "2026-09-18",
    "contracts": 200,
    "current_premium": 6.2,
    "original_premium": 6.2,
    "trade_date": "2026-02-19"
  },
  {
    "symbol": "AXON",
    "strike": 300.0,
    "expiry": "2026-09-18",
    "contracts": 500,
    "current_premium": 9.4,
    "original_premium": 9.4,
    "trade_date": "2026-02-19"
  },
  {
    "symbol": "BA",
    "strike": 205.0,
    "expiry": "2026-04-02",
    "contracts": 3400,
    "current_premium": 2.01,
    "original_premium": 2.01,
    "trade_date": "2026-02-19"
  },
  {
    "symbol": "CCJ",
    "strike": 90.0,
    "expiry": "2026-06-18",
    "contracts": 3375,
    "current_premium": 4.08,
    "original_premium": 4.08,
    "trade_date": "2026-02-19"
  },
  {
    "symbol": "CMPS",
    "strike": 8.0,
    "expiry": "2026-04-17",
    "contracts": 4000,
    "current_premium": 1.35,
    "original_premium": 1.35,
    "trade_date": "2026-02-19"
  },
  {
    "symbol": "CORT",
    "strike": 35.0,
    "expiry": "2026-04-17",
    "contracts": 5000,
    "current_premium": 2.35,
    "original_premium": 2.35,
    "trade_date": "2026-02-19"
  },
  {
    "symbol": "DAL",
    "strike": 65.0,
    "expiry": "2026-03-20",
    "contracts": 2500,
    "current_premium": 1.21,
    "original_premium": 1.21,
    "trade_date": "2026-02-19"
  },
  {
    "symbol": "ETN",
    "strike": 330.0,
    "expiry": "2026-03-27",
    "contracts": 2675,
    "current_premium": 3.0,
    "original_premium": 3.0,
    "trade_date": "2026-02-19"
  },
  {
    "symbol": "EWY",
    "strike": 130.0,
    "expiry": "2026-03-06",
    "contracts": 4000,
    "current_premium": 1.18,
    "original_premium": 1.18,
    "trade_date": "2026-02-19"
  },
  {
    "symbol": "FTI",
    "strike": 55.0,
    "expiry": "2026-04-17",
    "contracts": 2000,
    "current_premium": 0.55,
    "original_premium": 0.55,
    "trade_date": "2026-02-19"
  },
  {
    "symbol": "FUN",
    "strike": 15.0,
    "expiry": "2026-03-20",
    "contracts": 1900,
    "current_premium": 0.45,
    "original_premium": 0.45,
    "trade_date": "2026-02-19"
  },
  {
    "symbol": "IBRX",
    "strike": 6.0,
    "expiry": "2026-05-15",
    "contracts": 12000,
    "current_premium": 0.53,
    "original_premium": 0.53,
    "trade_date": "2026-02-19"
  },
  {
    "symbol": "INTC",
    "strike": 44.0,
    "expiry": "2026-04-17",
    "contracts": 7500,
    "current_premium": 3.22,
    "original_premium": 3.22,
    "trade_date": "2026-02-19"
  },
  {
    "symbol": "INTC",
    "strike": 42.0,
    "expiry": "2027-01-15",
    "contracts": 3000,
    "current_premium": 7.4,
    "original_premium": 7.4,
    "trade_date": "2026-02-19"
  },
  {
    "symbol": "ISRG",
    "strike": 450.0,
    "expiry": "2026-04-02",
    "contracts": 1550,
    "current_premium": 5.17,
    "original_premium": 5.17,
    "trade_date": "2026-02-19"
  },
  {
    "symbol": "KO",
    "strike": 72.5,
    "expiry": "2026-05-15",
    "contracts": 2750,
    "current_premium": 0.67,
    "original_premium": 0.67,
    "trade_date": "2026-02-19"
  },
  {
    "symbol": "NNE",
    "strike": 21.0,
    "expiry": "2026-04-17",
    "contracts": 2300,
    "current_premium": 1.12,
    "original_premium": 1.12,
    "trade_date": "2026-02-19"
  },
  {
    "symbol": "NOW",
    "strike": 85.0,
    "expiry": "2026-04-17",
    "contracts": 1150,
    "current_premium": 1.12,
    "original_premium": 1.12,
    "trade_date": "2026-02-19"
  },
  {
    "symbol": "PANW",
    "strike": 150.0,
    "expiry": "2026-08-21",
    "contracts": 750,
    "current_premium": 15.95,
    "original_premium": 15.95,
    "trade_date": "2026-02-19"
  },
  {
    "symbol": "RIOT",
    "strike": 11.5,
    "expiry": "2026-04-02",
    "contracts": 2000,
    "current_premium": 0.39,
    "original_premium": 0.39,
    "trade_date": "2026-02-19"
  },
  {
    "symbol": "RTX",
    "strike": 175.0,
    "expiry": "2026-08-21",
    "contracts": 400,
    "current_premium": 8.25,
    "original_premium": 8.25,
    "trade_date": "2026-02-19"
  },
  {
    "symbol": "TARS",
    "strike": 60.0,
    "expiry": "2026-04-17",
    "contracts": 2000,
    "current_premium": 1.75,
    "original_premium": 1.75,
    "trade_date": "2026-02-19"
  },
  {
    "symbol": "TLT",
    "strike": 84.0,
    "expiry": "2027-02-19",
    "contracts": 4900,
    "current_premium": 1.7,
    "original_premium": 1.7,
    "trade_date": "2026-02-19"
  },
  {
    "symbol": "WMT",
    "strike": 115.0,
    "expiry": "2026-04-17",
    "contracts": 9700,
    "current_premium": 1.58,
    "original_premium": 1.58,
    "trade_date": "2026-02-19"
  },
  {
    "symbol": "XERS",
    "strike": 5.0,
    "expiry": "2026-07-17",
    "contracts": 4000,
    "current_premium": 0.35,
    "original_premium": 0.35,
    "trade_date": "2026-02-19"
  },
  {
    "symbol": "ABT",
    "strike": 105.0,
    "expiry": "2026-03-20",
    "contracts": 5000,
    "current_premium": 0.36,
    "original_premium": 0.36,
    "trade_date": "2026-02-20"
  },
  {
    "symbol": "AR",
    "strike": 29.0,
    "expiry": "2026-03-27",
    "contracts": 23000,
    "current_premium": 0.17,
    "original_premium": 0.17,
    "trade_date": "2026-02-20"
  },
  {
    "symbol": "ARDX",
    "strike": 5.0,
    "expiry": "2026-07-17",
    "contracts": 2000,
    "current_premium": 0.4,
    "original_premium": 0.4,
    "trade_date": "2026-02-20"
  },
  {
    "symbol": "AVGO",
    "strike": 250.0,
    "expiry": "2026-04-17",
    "contracts": 5000,
    "current_premium": 4.45,
    "original_premium": 4.45,
    "trade_date": "2026-02-20"
  },
  {
    "symbol": "AVGO",
    "strike": 230.0,
    "expiry": "2026-05-15",
    "contracts": 1260,
    "current_premium": 4.12,
    "original_premium": 4.12,
    "trade_date": "2026-02-20"
  },
  {
    "symbol": "BABA",
    "strike": 140.0,
    "expiry": "2026-02-27",
    "contracts": 2500,
    "current_premium": 0.08,
    "original_premium": 0.08,
    "trade_date": "2026-02-20"
  },
  {
    "symbol": "BABA",
    "strike": 125.0,
    "expiry": "2026-09-18",
    "contracts": 1200,
    "current_premium": 6.88,
    "original_premium": 6.88,
    "trade_date": "2026-02-20"
  },
  {
    "symbol": "BE",
    "strike": 150.0,
    "expiry": "2026-03-20",
    "contracts": 1500,
    "current_premium": 10.68,
    "original_premium": 10.68,
    "trade_date": "2026-02-20"
  },
  {
    "symbol": "BP",
    "strike": 37.0,
    "expiry": "2026-03-06",
    "contracts": 1875,
    "current_premium": 0.34,
    "original_premium": 0.34,
    "trade_date": "2026-02-20"
  },
  {
    "symbol": "BRKB",
    "strike": 495.0,
    "expiry": "2026-03-20",
    "contracts": 2000,
    "current_premium": 0.0,
    "original_premium": null,
    "trade_date": "2026-02-20"
  },
  {
    "symbol": "C",
    "strike": 95.0,
    "expiry": "2026-11-20",
    "contracts": 600,
    "current_premium": 5.05,
    "original_premium": 5.05,
    "trade_date": "2026-02-20"
  },
  {
    "symbol": "CC",
    "strike": 14.0,
    "expiry": "2026-07-17",
    "contracts": 1750,
    "current_premium": 1.38,
    "original_premium": 1.38,
    "trade_date": "2026-02-20"
  },
  {
    "symbol": "CRDO",
    "strike": 95.0,
    "expiry": "2026-08-21",
    "contracts": 400,
    "current_premium": 16.45,
    "original_premium": 16.45,
    "trade_date": "2026-02-20"
  },
  {
    "symbol": "CVNA",
    "strike": 275.0,
    "expiry": "2026-02-27",
    "contracts": 5000,
    "current_premium": 0.09,
    "original_premium": 0.09,
    "trade_date": "2026-02-20"
  },
  {
    "symbol": "CVX",
    "strike": 175.0,
    "expiry": "2026-03-20",
    "contracts": 2500,
    "current_premium": 1.71,
    "original_premium": 1.71,
    "trade_date": "2026-02-20"
  },
  {
    "symbol": "DIS",
    "strike": 95.0,
    "expiry": "2026-04-02",
    "contracts": 7250,
    "current_premium": 0.61,
    "original_premium": 0.61,
    "trade_date": "2026-02-20"
  },
  {
    "symbol": "EBAY",
    "strike": 86.0,
    "expiry": "2026-02-27",
    "contracts": 2000,
    "current_premium": 0.2,
    "original_premium": 0.2,
    "trade_date": "2026-02-20"
  },
  {
    "symbol": "FND",
    "strike": 55.0,
    "expiry": "2026-04-17",
    "contracts": 13200,
    "current_premium": 0.7,
    "original_premium": 0.7,
    "trade_date": "2026-02-20"
  },
  {
    "symbol": "FVRR",
    "strike": 10.0,
    "expiry": "2027-01-15",
    "contracts": 2000,
    "current_premium": 1.73,
    "original_premium": 1.73,
    "trade_date": "2026-02-20"
  },
  {
    "symbol": "GDX",
    "strike": 90.0,
    "expiry": "2026-03-20",
    "contracts": 1500,
    "current_premium": 0.32,
    "original_premium": 0.32,
    "trade_date": "2026-02-20"
  },
  {
    "symbol": "INTU",
    "strike": 300.0,
    "expiry": "2026-09-18",
    "contracts": 400,
    "current_premium": 19.85,
    "original_premium": 19.85,
    "trade_date": "2026-02-20"
  },
  {
    "symbol": "ISRG",
    "strike": 440.0,
    "expiry": "2026-03-27",
    "contracts": 1575,
    "current_premium": 2.43,
    "original_premium": 2.43,
    "trade_date": "2026-02-20"
  },
  {
    "symbol": "JNJ",
    "strike": 280.0,
    "expiry": "2026-12-18",
    "contracts": 450,
    "current_premium": 40.88,
    "original_premium": 40.88,
    "trade_date": "2026-02-20"
  },
  {
    "symbol": "MGM",
    "strike": 30.0,
    "expiry": "2028-01-21",
    "contracts": 2000,
    "current_premium": 4.6,
    "original_premium": 4.6,
    "trade_date": "2026-02-20"
  },
  {
    "symbol": "MS",
    "strike": 160.0,
    "expiry": "2026-02-27",
    "contracts": 5000,
    "current_premium": 0.06,
    "original_premium": 0.06,
    "trade_date": "2026-02-20"
  },
  {
    "symbol": "MSTR",
    "strike": 126.0,
    "expiry": "2026-02-27",
    "contracts": 1000,
    "current_premium": 0.35,
    "original_premium": 0.35,
    "trade_date": "2026-02-20"
  },
  {
    "symbol": "MU",
    "strike": 410.0,
    "expiry": "2026-03-20",
    "contracts": 2000,
    "current_premium": 29.38,
    "original_premium": 29.38,
    "trade_date": "2026-02-20"
  },
  {
    "symbol": "NUAI",
    "strike": 4.5,
    "expiry": "2026-03-20",
    "contracts": 1650,
    "current_premium": 0.55,
    "original_premium": 0.55,
    "trade_date": "2026-02-20"
  },
  {
    "symbol": "NVDA",
    "strike": 160.0,
    "expiry": "2026-06-18",
    "contracts": 1000,
    "current_premium": 8.05,
    "original_premium": 8.05,
    "trade_date": "2026-02-20"
  },
  {
    "symbol": "OKTA",
    "strike": 82.5,
    "expiry": "2026-05-15",
    "contracts": 1500,
    "current_premium": 11.68,
    "original_premium": 11.68,
    "trade_date": "2026-02-20"
  },
  {
    "symbol": "VWO",
    "strike": 54.0,
    "expiry": "2026-05-15",
    "contracts": 1670,
    "current_premium": 0.8,
    "original_premium": 0.8,
    "trade_date": "2026-02-20"
  },
  {
    "symbol": "WDC",
    "strike": 260.0,
    "expiry": "2026-06-18",
    "contracts": 400,
    "current_premium": 38.85,
    "original_premium": 38.85,
    "trade_date": "2026-02-20"
  },
  {
    "symbol": "WMT",
    "strike": 110.0,
    "expiry": "2026-03-20",
    "contracts": 9000,
    "current_premium": 0.3,
    "original_premium": 0.3,
    "trade_date": "2026-02-20"
  },
  {
    "symbol": "XLE",
    "strike": 52.0,
    "expiry": "2026-03-20",
    "contracts": 7000,
    "current_premium": 0.53,
    "original_premium": 0.53,
    "trade_date": "2026-02-20"
  },
  {
    "symbol": "AAPL",
    "strike": 260.0,
    "expiry": "2026-04-17",
    "contracts": 10000,
    "current_premium": 4.95,
    "original_premium": 4.95,
    "trade_date": "2026-02-23"
  },
  {
    "symbol": "AMGN",
    "strike": 340.0,
    "expiry": "2026-06-18",
    "contracts": 1100,
    "current_premium": 8.57,
    "original_premium": 8.57,
    "trade_date": "2026-02-23"
  },
  {
    "symbol": "AMT",
    "strike": 190.0,
    "expiry": "2026-04-17",
    "contracts": 1300,
    "current_premium": 10.05,
    "original_premium": 10.05,
    "trade_date": "2026-02-23"
  },
  {
    "symbol": "ANET",
    "strike": 100.0,
    "expiry": "2027-03-19",
    "contracts": 500,
    "current_premium": 0.0,
    "original_premium": null,
    "trade_date": "2026-02-23"
  },
  {
    "symbol": "AS",
    "strike": 37.5,
    "expiry": "2026-03-20",
    "contracts": 2375,
    "current_premium": 1.25,
    "original_premium": 1.25,
    "trade_date": "2026-02-23"
  },
  {
    "symbol": "ASTS",
    "strike": 80.0,
    "expiry": "2027-01-15",
    "contracts": 2400,
    "current_premium": 25.88,
    "original_premium": 25.88,
    "trade_date": "2026-02-23"
  },
  {
    "symbol": "BE",
    "strike": 110.0,
    "expiry": "2026-05-15",
    "contracts": 1400,
    "current_premium": 10.02,
    "original_premium": 10.02,
    "trade_date": "2026-02-23"
  },
  {
    "symbol": "CMG",
    "strike": 32.0,
    "expiry": "2026-03-20",
    "contracts": 12000,
    "current_premium": 0.0,
    "original_premium": null,
    "trade_date": "2026-02-23"
  },
  {
    "symbol": "COP",
    "strike": 95.0,
    "expiry": "2026-09-18",
    "contracts": 2500,
    "current_premium": 3.66,
    "original_premium": 3.66,
    "trade_date": "2026-02-23"
  },
  {
    "symbol": "CRM",
    "strike": 165.0,
    "expiry": "2026-02-27",
    "contracts": 1200,
    "current_premium": 0.01,
    "original_premium": 0.01,
    "trade_date": "2026-02-23"
  },
  {
    "symbol": "CTSH",
    "strike": 60.0,
    "expiry": "2026-03-20",
    "contracts": 3400,
    "current_premium": 1.0,
    "original_premium": 1.0,
    "trade_date": "2026-02-23"
  },
  {
    "symbol": "DHR",
    "strike": 195.0,
    "expiry": "2026-03-20",
    "contracts": 5000,
    "current_premium": 1.55,
    "original_premium": 1.55,
    "trade_date": "2026-02-23"
  },
  {
    "symbol": "ETN",
    "strike": 320.0,
    "expiry": "2026-03-27",
    "contracts": 2720,
    "current_premium": 0.0,
    "original_premium": null,
    "trade_date": "2026-02-23"
  },
  {
    "symbol": "EWY",
    "strike": 115.0,
    "expiry": "2026-07-17",
    "contracts": 1000,
    "current_premium": 5.8,
    "original_premium": 5.8,
    "trade_date": "2026-02-23"
  },
  {
    "symbol": "FND",
    "strike": 55.0,
    "expiry": "2026-04-17",
    "contracts": 13500,
    "current_premium": 0.7,
    "original_premium": 0.7,
    "trade_date": "2026-02-23"
  },
  {
    "symbol": "FND",
    "strike": 60.0,
    "expiry": "2026-06-18",
    "contracts": 2000,
    "current_premium": 3.48,
    "original_premium": 3.48,
    "trade_date": "2026-02-23"
  },
  {
    "symbol": "GILD",
    "strike": 140.0,
    "expiry": "2026-05-15",
    "contracts": 600,
    "current_premium": 6.33,
    "original_premium": 6.33,
    "trade_date": "2026-02-23"
  },
  {
    "symbol": "IBIT",
    "strike": 35.0,
    "expiry": "2026-03-20",
    "contracts": 1000,
    "current_premium": 0.77,
    "original_premium": 0.77,
    "trade_date": "2026-02-23"
  },
  {
    "symbol": "IGV",
    "strike": 60.0,
    "expiry": "2026-12-18",
    "contracts": 5000,
    "current_premium": 2.9,
    "original_premium": null,
    "trade_date": "2026-02-23"
  },
  {
    "symbol": "JPM",
    "strike": 302.5,
    "expiry": "2026-02-27",
    "contracts": 2525,
    "current_premium": 0.66,
    "original_premium": 0.66,
    "trade_date": "2026-02-23"
  },
  {
    "symbol": "JPM",
    "strike": 255.0,
    "expiry": "2026-03-27",
    "contracts": 1500,
    "current_premium": 0.69,
    "original_premium": 0.69,
    "trade_date": "2026-02-23"
  },
  {
    "symbol": "LULU",
    "strike": 175.0,
    "expiry": "2026-02-27",
    "contracts": 1000,
    "current_premium": 0.13,
    "original_premium": 0.13,
    "trade_date": "2026-02-23"
  },
  {
    "symbol": "MDT",
    "strike": 97.0,
    "expiry": "2026-03-06",
    "contracts": 1250,
    "current_premium": 1.19,
    "original_premium": 1.19,
    "trade_date": "2026-02-23"
  },
  {
    "symbol": "MKC",
    "strike": 65.0,
    "expiry": "2026-04-17",
    "contracts": 4000,
    "current_premium": 1.23,
    "original_premium": 1.23,
    "trade_date": "2026-02-23"
  },
  {
    "symbol": "MNDY",
    "strike": 70.0,
    "expiry": "2027-01-15",
    "contracts": 650,
    "current_premium": 14.25,
    "original_premium": 14.25,
    "trade_date": "2026-02-23"
  },
  {
    "symbol": "MNST",
    "strike": 72.5,
    "expiry": "2026-06-18",
    "contracts": 2550,
    "current_premium": 1.45,
    "original_premium": 1.45,
    "trade_date": "2026-02-23"
  },
  {
    "symbol": "MSFT",
    "strike": 320.0,
    "expiry": "2027-03-19",
    "contracts": 1100,
    "current_premium": 16.52,
    "original_premium": 16.52,
    "trade_date": "2026-02-23"
  },
  {
    "symbol": "NVDA",
    "strike": 150.0,
    "expiry": "2026-03-20",
    "contracts": 2000,
    "current_premium": 0.7,
    "original_premium": 0.7,
    "trade_date": "2026-02-23"
  },
  {
    "symbol": "NVO",
    "strike": 35.0,
    "expiry": "2026-05-15",
    "contracts": 10000,
    "current_premium": 2.24,
    "original_premium": 2.24,
    "trade_date": "2026-02-23"
  },
  {
    "symbol": "OKTA",
    "strike": 60.0,
    "expiry": "2028-01-21",
    "contracts": 600,
    "current_premium": 10.5,
    "original_premium": 10.5,
    "trade_date": "2026-02-23"
  },
  {
    "symbol": "ORCL",
    "strike": 115.0,
    "expiry": "2026-11-20",
    "contracts": 450,
    "current_premium": 12.43,
    "original_premium": 12.43,
    "trade_date": "2026-02-23"
  },
  {
    "symbol": "ORCL",
    "strike": 130.0,
    "expiry": "2027-01-15",
    "contracts": 1500,
    "current_premium": 20.3,
    "original_premium": 20.3,
    "trade_date": "2026-02-23"
  },
  {
    "symbol": "PLTR",
    "strike": 125.0,
    "expiry": "2026-02-27",
    "contracts": 1100,
    "current_premium": 0.07,
    "original_premium": 0.07,
    "trade_date": "2026-02-23"
  },
  {
    "symbol": "PLTR",
    "strike": 95.0,
    "expiry": "2027-03-19",
    "contracts": 2150,
    "current_premium": 11.62,
    "original_premium": 11.62,
    "trade_date": "2026-02-23"
  },
  {
    "symbol": "PSX",
    "strike": 140.0,
    "expiry": "2026-05-15",
    "contracts": 2275,
    "current_premium": 4.2,
    "original_premium": 4.2,
    "trade_date": "2026-02-23"
  },
  {
    "symbol": "RKT",
    "strike": 17.0,
    "expiry": "2026-03-06",
    "contracts": 1000,
    "current_premium": 0.7,
    "original_premium": 0.7,
    "trade_date": "2026-02-23"
  },
  {
    "symbol": "ROK",
    "strike": 350.0,
    "expiry": "2026-04-17",
    "contracts": 2715,
    "current_premium": 2.42,
    "original_premium": 2.42,
    "trade_date": "2026-02-23"
  },
  {
    "symbol": "SEI",
    "strike": 40.0,
    "expiry": "2026-03-20",
    "contracts": 1275,
    "current_premium": 0.65,
    "original_premium": 0.65,
    "trade_date": "2026-02-23"
  },
  {
    "symbol": "SLV",
    "strike": 55.5,
    "expiry": "2027-01-15",
    "contracts": 1300,
    "current_premium": 5.08,
    "original_premium": 5.08,
    "trade_date": "2026-02-23"
  },
  {
    "symbol": "SU",
    "strike": 45.0,
    "expiry": "2026-06-18",
    "contracts": 1000,
    "current_premium": 0.68,
    "original_premium": 0.68,
    "trade_date": "2026-02-23"
  },
  {
    "symbol": "TEAM",
    "strike": 70.0,
    "expiry": "2026-02-27",
    "contracts": 1240,
    "current_premium": 0.05,
    "original_premium": 0.05,
    "trade_date": "2026-02-23"
  },
  {
    "symbol": "TEM",
    "strike": 50.0,
    "expiry": "2026-09-18",
    "contracts": 2000,
    "current_premium": 8.45,
    "original_premium": 8.45,
    "trade_date": "2026-02-23"
  },
  {
    "symbol": "TRIN",
    "strike": 15.0,
    "expiry": "2026-03-20",
    "contracts": 3000,
    "current_premium": 0.38,
    "original_premium": 0.38,
    "trade_date": "2026-02-23"
  },
  {
    "symbol": "TROW",
    "strike": 85.0,
    "expiry": "2026-03-20",
    "contracts": 2000,
    "current_premium": 0.38,
    "original_premium": 0.38,
    "trade_date": "2026-02-23"
  },
  {
    "symbol": "TSLA",
    "strike": 320.0,
    "expiry": "2026-03-20",
    "contracts": 1200,
    "current_premium": 0.88,
    "original_premium": 0.88,
    "trade_date": "2026-02-23"
  },
  {
    "symbol": "TSLA",
    "strike": 370.0,
    "expiry": "2026-04-17",
    "contracts": 7000,
    "current_premium": 10.22,
    "original_premium": 10.22,
    "trade_date": "2026-02-23"
  },
  {
    "symbol": "TSM",
    "strike": 360.0,
    "expiry": "2026-04-17",
    "contracts": 6000,
    "current_premium": 16.18,
    "original_premium": 16.18,
    "trade_date": "2026-02-23"
  },
  {
    "symbol": "UAL",
    "strike": 95.0,
    "expiry": "2026-04-17",
    "contracts": 2000,
    "current_premium": 2.42,
    "original_premium": 2.42,
    "trade_date": "2026-02-23"
  },
  {
    "symbol": "UBER",
    "strike": 42.5,
    "expiry": "2027-01-15",
    "contracts": 2200,
    "current_premium": 1.03,
    "original_premium": 1.03,
    "trade_date": "2026-02-23"
  },
  {
    "symbol": "USAS",
    "strike": 8.0,
    "expiry": "2026-03-20",
    "contracts": 2500,
    "current_premium": 0.38,
    "original_premium": 0.38,
    "trade_date": "2026-02-23"
  },
  {
    "symbol": "V",
    "strike": 270.0,
    "expiry": "2026-03-20",
    "contracts": 1400,
    "current_premium": 0.47,
    "original_premium": 0.47,
    "trade_date": "2026-02-23"
  },
  {
    "symbol": "VALE",
    "strike": 15.0,
    "expiry": "2027-01-15",
    "contracts": 2050,
    "current_premium": 1.32,
    "original_premium": 1.32,
    "trade_date": "2026-02-23"
  },
  {
    "symbol": "VEL",
    "strike": 20.0,
    "expiry": "2026-03-20",
    "contracts": 4000,
    "current_premium": 1.82,
    "original_premium": 1.82,
    "trade_date": "2026-02-23"
  },
  {
    "symbol": "AFRM",
    "strike": 42.5,
    "expiry": "2026-06-18",
    "contracts": 900,
    "current_premium": 3.97,
    "original_premium": 3.97,
    "trade_date": "2026-02-25"
  },
  {
    "symbol": "AG",
    "strike": 21.0,
    "expiry": "2026-07-17",
    "contracts": 5000,
    "current_premium": 1.7,
    "original_premium": 1.7,
    "trade_date": "2026-02-25"
  },
  {
    "symbol": "AMD",
    "strike": 150.0,
    "expiry": "2026-04-17",
    "contracts": 6000,
    "current_premium": 1.67,
    "original_premium": 1.67,
    "trade_date": "2026-02-25"
  },
  {
    "symbol": "ANIP",
    "strike": 75.0,
    "expiry": "2026-04-17",
    "contracts": 2000,
    "current_premium": 4.35,
    "original_premium": 4.35,
    "trade_date": "2026-02-25"
  },
  {
    "symbol": "AR",
    "strike": 27.0,
    "expiry": "2026-03-27",
    "contracts": 15000,
    "current_premium": 0.15,
    "original_premium": 0.15,
    "trade_date": "2026-02-25"
  },
  {
    "symbol": "AVGO",
    "strike": 230.0,
    "expiry": "2026-04-02",
    "contracts": 3000,
    "current_premium": 1.55,
    "original_premium": 1.55,
    "trade_date": "2026-02-25"
  },
  {
    "symbol": "BBY",
    "strike": 60.0,
    "expiry": "2028-01-21",
    "contracts": 480,
    "current_premium": 12.93,
    "original_premium": 12.93,
    "trade_date": "2026-02-25"
  },
  {
    "symbol": "CELH",
    "strike": 45.5,
    "expiry": "2026-02-27",
    "contracts": 1800,
    "current_premium": 0.01,
    "original_premium": 0.01,
    "trade_date": "2026-02-25"
  },
  {
    "symbol": "CRWD",
    "strike": 320.0,
    "expiry": "2026-04-17",
    "contracts": 500,
    "current_premium": 8.88,
    "original_premium": 8.88,
    "trade_date": "2026-02-25"
  },
  {
    "symbol": "CRWD",
    "strike": 320.0,
    "expiry": "2028-01-21",
    "contracts": 200,
    "current_premium": 60.48,
    "original_premium": 60.48,
    "trade_date": "2026-02-25"
  },
  {
    "symbol": "EOSE",
    "strike": 11.0,
    "expiry": "2026-03-20",
    "contracts": 2500,
    "current_premium": 4.17,
    "original_premium": 4.17,
    "trade_date": "2026-02-25"
  },
  {
    "symbol": "ESLT",
    "strike": 640.0,
    "expiry": "2026-09-18",
    "contracts": 110,
    "current_premium": 0.0,
    "original_premium": null,
    "trade_date": "2026-02-25"
  },
  {
    "symbol": "FCX",
    "strike": 64.0,
    "expiry": "2026-02-27",
    "contracts": 1000,
    "current_premium": 0.07,
    "original_premium": 0.07,
    "trade_date": "2026-02-25"
  },
  {
    "symbol": "FCX",
    "strike": 61.0,
    "expiry": "2026-03-20",
    "contracts": 3300,
    "current_premium": 1.06,
    "original_premium": null,
    "trade_date": "2026-02-25"
  },
  {
    "symbol": "FUTU",
    "strike": 140.0,
    "expiry": "2026-04-17",
    "contracts": 800,
    "current_premium": 5.47,
    "original_premium": 5.47,
    "trade_date": "2026-02-25"
  },
  {
    "symbol": "GFI",
    "strike": 50.0,
    "expiry": "2027-01-15",
    "contracts": 1000,
    "current_premium": 7.9,
    "original_premium": 7.9,
    "trade_date": "2026-02-25"
  },
  {
    "symbol": "GLW",
    "strike": 136.0,
    "expiry": "2026-03-20",
    "contracts": 5300,
    "current_premium": 4.35,
    "original_premium": null,
    "trade_date": "2026-02-25"
  },
  {
    "symbol": "HD",
    "strike": 350.0,
    "expiry": "2026-03-20",
    "contracts": 1000,
    "current_premium": 2.19,
    "original_premium": 2.19,
    "trade_date": "2026-02-25"
  },
  {
    "symbol": "HL",
    "strike": 10.0,
    "expiry": "2027-01-15",
    "contracts": 2500,
    "current_premium": 0.69,
    "original_premium": 0.69,
    "trade_date": "2026-02-25"
  },
  {
    "symbol": "IGV",
    "strike": 75.0,
    "expiry": "2026-03-20",
    "contracts": 1000,
    "current_premium": 0.85,
    "original_premium": 0.85,
    "trade_date": "2026-02-25"
  },
  {
    "symbol": "IGV",
    "strike": 70.0,
    "expiry": "2026-06-18",
    "contracts": 5000,
    "current_premium": 2.17,
    "original_premium": 2.17,
    "trade_date": "2026-02-25"
  },
  {
    "symbol": "LLY",
    "strike": 890.0,
    "expiry": "2026-04-17",
    "contracts": 950,
    "current_premium": 0.0,
    "original_premium": null,
    "trade_date": "2026-02-25"
  },
  {
    "symbol": "LMND",
    "strike": 50.0,
    "expiry": "2026-09-18",
    "contracts": 1000,
    "current_premium": 9.7,
    "original_premium": 9.7,
    "trade_date": "2026-02-25"
  },
  {
    "symbol": "LYFT",
    "strike": 13.0,
    "expiry": "2027-03-19",
    "contracts": 1300,
    "current_premium": 2.64,
    "original_premium": 2.64,
    "trade_date": "2026-02-25"
  },
  {
    "symbol": "NVDA",
    "strike": 202.5,
    "expiry": "2026-03-20",
    "contracts": 1300,
    "current_premium": 0.0,
    "original_premium": null,
    "trade_date": "2026-02-25"
  },
  {
    "symbol": "PBR",
    "strike": 12.0,
    "expiry": "2026-10-16",
    "contracts": 1350,
    "current_premium": 0.0,
    "original_premium": null,
    "trade_date": "2026-02-25"
  },
  {
    "symbol": "PGEN",
    "strike": 4.0,
    "expiry": "2026-03-20",
    "contracts": 1000,
    "current_premium": 0.55,
    "original_premium": 0.55,
    "trade_date": "2026-02-25"
  },
  {
    "symbol": "PRU",
    "strike": 90.0,
    "expiry": "2026-04-17",
    "contracts": 2000,
    "current_premium": 0.0,
    "original_premium": null,
    "trade_date": "2026-02-25"
  },
  {
    "symbol": "QCOM",
    "strike": 140.0,
    "expiry": "2026-04-17",
    "contracts": 1500,
    "current_premium": 4.72,
    "original_premium": 4.72,
    "trade_date": "2026-02-25"
  },
  {
    "symbol": "RACE",
    "strike": 370.0,
    "expiry": "2026-12-18",
    "contracts": 200,
    "current_premium": 36.3,
    "original_premium": 36.3,
    "trade_date": "2026-02-25"
  },
  {
    "symbol": "UBER",
    "strike": 55.0,
    "expiry": "2027-01-15",
    "contracts": 1000,
    "current_premium": 3.16,
    "original_premium": 3.16,
    "trade_date": "2026-02-25"
  },
  {
    "symbol": "V",
    "strike": 275.0,
    "expiry": "2026-05-15",
    "contracts": 1200,
    "current_premium": 3.3,
    "original_premium": 3.3,
    "trade_date": "2026-02-25"
  },
  {
    "symbol": "VZ",
    "strike": 47.0,
    "expiry": "2026-05-15",
    "contracts": 3300,
    "current_premium": 1.46,
    "original_premium": 1.46,
    "trade_date": "2026-02-25"
  },
  {
    "symbol": "WSM",
    "strike": 175.0,
    "expiry": "2026-04-17",
    "contracts": 2000,
    "current_premium": 2.8,
    "original_premium": 2.8,
    "trade_date": "2026-02-25"
  },
  {
    "symbol": "WULF",
    "strike": 11.0,
    "expiry": "2026-06-18",
    "contracts": 2200,
    "current_premium": 0.84,
    "original_premium": 0.84,
    "trade_date": "2026-02-25"
  },
  {
    "symbol": "XLF",
    "strike": 50.0,
    "expiry": "2026-09-18",
    "contracts": 3000,
    "current_premium": 1.91,
    "original_premium": 1.91,
    "trade_date": "2026-02-25"
  },
  {
    "symbol": "XOM",
    "strike": 135.0,
    "expiry": "2026-12-18",
    "contracts": 1000,
    "current_premium": 8.5,
    "original_premium": 8.5,
    "trade_date": "2026-02-25"
  },
  {
    "symbol": "AAL",
    "strike": 8.0,
    "expiry": "2027-12-17",
    "contracts": 2900,
    "current_premium": 0.77,
    "original_premium": 0.77,
    "trade_date": "2026-02-25"
  },
  {
    "symbol": "AAPL",
    "strike": 270.0,
    "expiry": "2026-04-17",
    "contracts": 10000,
    "current_premium": 8.03,
    "original_premium": 8.03,
    "trade_date": "2026-02-25"
  },
  {
    "symbol": "ADI",
    "strike": 332.5,
    "expiry": "2026-03-06",
    "contracts": 2900,
    "current_premium": 1.18,
    "original_premium": 1.18,
    "trade_date": "2026-02-25"
  },
  {
    "symbol": "BTDR",
    "strike": 8.0,
    "expiry": "2026-03-06",
    "contracts": 1000,
    "current_premium": 0.5,
    "original_premium": 0.5,
    "trade_date": "2026-02-25"
  },
  {
    "symbol": "BX",
    "strike": 100.0,
    "expiry": "2026-11-20",
    "contracts": 1250,
    "current_premium": 9.75,
    "original_premium": null,
    "trade_date": "2026-02-25"
  },
  {
    "symbol": "BX",
    "strike": 100.0,
    "expiry": "2027-01-15",
    "contracts": 2150,
    "current_premium": 10.18,
    "original_premium": 10.18,
    "trade_date": "2026-02-25"
  },
  {
    "symbol": "COHR",
    "strike": 300.0,
    "expiry": "2027-01-15",
    "contracts": 4000,
    "current_premium": 100.25,
    "original_premium": 100.25,
    "trade_date": "2026-02-25"
  },
  {
    "symbol": "CYTK",
    "strike": 50.0,
    "expiry": "2026-04-17",
    "contracts": 1500,
    "current_premium": 1.93,
    "original_premium": 1.93,
    "trade_date": "2026-02-25"
  },
  {
    "symbol": "DHI",
    "strike": 135.0,
    "expiry": "2026-03-27",
    "contracts": 3000,
    "current_premium": 0.57,
    "original_premium": 0.57,
    "trade_date": "2026-02-25"
  },
  {
    "symbol": "EMR",
    "strike": 130.0,
    "expiry": "2026-06-18",
    "contracts": 1450,
    "current_premium": 2.85,
    "original_premium": 2.85,
    "trade_date": "2026-02-25"
  },
  {
    "symbol": "EW",
    "strike": 75.0,
    "expiry": "2026-05-15",
    "contracts": 2585,
    "current_premium": 1.35,
    "original_premium": 1.35,
    "trade_date": "2026-02-25"
  },
  {
    "symbol": "FSLR",
    "strike": 155.0,
    "expiry": "2026-04-17",
    "contracts": 4500,
    "current_premium": 2.17,
    "original_premium": 2.17,
    "trade_date": "2026-02-25"
  },
  {
    "symbol": "GSK",
    "strike": 60.0,
    "expiry": "2026-04-17",
    "contracts": 2685,
    "current_premium": 3.1,
    "original_premium": 3.1,
    "trade_date": "2026-02-25"
  },
  {
    "symbol": "HOOD",
    "strike": 60.0,
    "expiry": "2026-03-20",
    "contracts": 5000,
    "current_premium": 0.5,
    "original_premium": 0.5,
    "trade_date": "2026-02-25"
  },
  {
    "symbol": "IBM",
    "strike": 220.0,
    "expiry": "2028-01-21",
    "contracts": 300,
    "current_premium": 30.9,
    "original_premium": 30.9,
    "trade_date": "2026-02-25"
  },
  {
    "symbol": "INTC",
    "strike": 40.0,
    "expiry": "2026-08-21",
    "contracts": 1500,
    "current_premium": 4.4,
    "original_premium": 4.4,
    "trade_date": "2026-02-25"
  },
  {
    "symbol": "LOW",
    "strike": 250.0,
    "expiry": "2026-03-20",
    "contracts": 3640,
    "current_premium": 1.79,
    "original_premium": 1.79,
    "trade_date": "2026-02-25"
  },
  {
    "symbol": "LOW",
    "strike": 245.0,
    "expiry": "2026-04-02",
    "contracts": 2925,
    "current_premium": 2.33,
    "original_premium": null,
    "trade_date": "2026-02-25"
  },
  {
    "symbol": "LRCX",
    "strike": 225.0,
    "expiry": "2026-02-27",
    "contracts": 1500,
    "current_premium": 0.43,
    "original_premium": 0.43,
    "trade_date": "2026-02-25"
  },
  {
    "symbol": "MSFT",
    "strike": 250.0,
    "expiry": "2026-12-18",
    "contracts": 1000,
    "current_premium": 3.5,
    "original_premium": 3.5,
    "trade_date": "2026-02-25"
  },
  {
    "symbol": "MU",
    "strike": 425.0,
    "expiry": "2026-03-06",
    "contracts": 5000,
    "current_premium": 22.25,
    "original_premium": 22.25,
    "trade_date": "2026-02-25"
  },
  {
    "symbol": "NFLX",
    "strike": 76.0,
    "expiry": "2026-02-27",
    "contracts": 1100,
    "current_premium": 0.01,
    "original_premium": 0.01,
    "trade_date": "2026-02-25"
  },
  {
    "symbol": "NOC",
    "strike": 640.0,
    "expiry": "2026-03-20",
    "contracts": 1500,
    "current_premium": 3.67,
    "original_premium": 3.67,
    "trade_date": "2026-02-25"
  },
  {
    "symbol": "ORCL",
    "strike": 140.0,
    "expiry": "2026-02-27",
    "contracts": 2700,
    "current_premium": 0.18,
    "original_premium": 0.18,
    "trade_date": "2026-02-25"
  },
  {
    "symbol": "OSG",
    "strike": 5.0,
    "expiry": "2026-08-21",
    "contracts": 3000,
    "current_premium": 0.0,
    "original_premium": null,
    "trade_date": "2026-02-25"
  },
  {
    "symbol": "PYPL",
    "strike": 40.0,
    "expiry": "2027-12-17",
    "contracts": 2000,
    "current_premium": 5.7,
    "original_premium": 5.7,
    "trade_date": "2026-02-25"
  },
  {
    "symbol": "RKT",
    "strike": 15.0,
    "expiry": "2026-04-17",
    "contracts": 1330,
    "current_premium": 0.67,
    "original_premium": 0.67,
    "trade_date": "2026-02-25"
  },
  {
    "symbol": "RSP",
    "strike": 190.0,
    "expiry": "2026-05-15",
    "contracts": 2500,
    "current_premium": 2.67,
    "original_premium": 2.67,
    "trade_date": "2026-02-25"
  },
  {
    "symbol": "SATS",
    "strike": 115.0,
    "expiry": "2027-01-15",
    "contracts": 900,
    "current_premium": 27.75,
    "original_premium": 27.75,
    "trade_date": "2026-02-25"
  },
  {
    "symbol": "SHLS",
    "strike": 5.0,
    "expiry": "2026-11-20",
    "contracts": 5000,
    "current_premium": 0.95,
    "original_premium": 0.95,
    "trade_date": "2026-02-25"
  },
  {
    "symbol": "SILJ",
    "strike": 37.0,
    "expiry": "2026-03-06",
    "contracts": 15000,
    "current_premium": 0.55,
    "original_premium": 0.55,
    "trade_date": "2026-02-25"
  },
  {
    "symbol": "SILJ",
    "strike": 35.0,
    "expiry": "2026-03-06",
    "contracts": 30000,
    "current_premium": 0.29,
    "original_premium": 0.29,
    "trade_date": "2026-02-25"
  },
  {
    "symbol": "SOFI",
    "strike": 18.0,
    "expiry": "2026-03-20",
    "contracts": 1000,
    "current_premium": 0.69,
    "original_premium": 0.69,
    "trade_date": "2026-02-25"
  },
  {
    "symbol": "VALE",
    "strike": 16.0,
    "expiry": "2026-03-20",
    "contracts": 1500,
    "current_premium": 0.2,
    "original_premium": 0.2,
    "trade_date": "2026-02-25"
  },
  {
    "symbol": "WBD",
    "strike": 27.0,
    "expiry": "2026-03-20",
    "contracts": 2500,
    "current_premium": 0.23,
    "original_premium": 0.23,
    "trade_date": "2026-02-25"
  },
  {
    "symbol": "ABBV",
    "strike": 200.0,
    "expiry": "2026-04-02",
    "contracts": 1900,
    "current_premium": 1.22,
    "original_premium": 1.22,
    "trade_date": "2026-02-26"
  },
  {
    "symbol": "ADBE",
    "strike": 250.0,
    "expiry": "2026-02-27",
    "contracts": 1450,
    "current_premium": 0.36,
    "original_premium": 0.36,
    "trade_date": "2026-02-26"
  },
  {
    "symbol": "BHP",
    "strike": 77.5,
    "expiry": "2026-04-17",
    "contracts": 600,
    "current_premium": 0.0,
    "original_premium": null,
    "trade_date": "2026-02-26"
  },
  {
    "symbol": "C",
    "strike": 108.0,
    "expiry": "2026-03-20",
    "contracts": 5000,
    "current_premium": 0.0,
    "original_premium": null,
    "trade_date": "2026-02-26"
  },
  {
    "symbol": "CSCO",
    "strike": 77.0,
    "expiry": "2026-02-27",
    "contracts": 2100,
    "current_premium": 0.15,
    "original_premium": 0.15,
    "trade_date": "2026-02-26"
  },
  {
    "symbol": "EOSE",
    "strike": 4.0,
    "expiry": "2026-08-21",
    "contracts": 2500,
    "current_premium": 0.51,
    "original_premium": null,
    "trade_date": "2026-02-26"
  },
  {
    "symbol": "ETN",
    "strike": 325.0,
    "expiry": "2026-03-27",
    "contracts": 1860,
    "current_premium": 0.0,
    "original_premium": null,
    "trade_date": "2026-02-26"
  },
  {
    "symbol": "FIGR",
    "strike": 35.0,
    "expiry": "2026-08-21",
    "contracts": 1000,
    "current_premium": 9.7,
    "original_premium": 9.7,
    "trade_date": "2026-02-26"
  },
  {
    "symbol": "GLD",
    "strike": 425.0,
    "expiry": "2026-05-15",
    "contracts": 24600,
    "current_premium": 5.6,
    "original_premium": 5.6,
    "trade_date": "2026-02-26"
  },
  {
    "symbol": "GOOGL",
    "strike": 310.0,
    "expiry": "2026-04-02",
    "contracts": 10000,
    "current_premium": 12.72,
    "original_premium": 12.72,
    "trade_date": "2026-02-26"
  },
  {
    "symbol": "INTC",
    "strike": 43.5,
    "expiry": "2026-02-27",
    "contracts": 7900,
    "current_premium": 0.15,
    "original_premium": 0.15,
    "trade_date": "2026-02-26"
  },
  {
    "symbol": "INTC",
    "strike": 48.0,
    "expiry": "2026-04-17",
    "contracts": 3725,
    "current_premium": 5.4,
    "original_premium": 5.4,
    "trade_date": "2026-02-26"
  },
  {
    "symbol": "LITE",
    "strike": 800.0,
    "expiry": "2027-01-15",
    "contracts": 1200,
    "current_premium": 307.55,
    "original_premium": 307.55,
    "trade_date": "2026-02-26"
  },
  {
    "symbol": "MU",
    "strike": 400.0,
    "expiry": "2026-03-13",
    "contracts": 5000,
    "current_premium": 15.92,
    "original_premium": 15.92,
    "trade_date": "2026-02-26"
  },
  {
    "symbol": "NTES",
    "strike": 105.0,
    "expiry": "2026-09-18",
    "contracts": 1500,
    "current_premium": 8.75,
    "original_premium": 8.75,
    "trade_date": "2026-02-26"
  },
  {
    "symbol": "NVDA",
    "strike": 145.0,
    "expiry": "2026-11-20",
    "contracts": 2000,
    "current_premium": 10.7,
    "original_premium": 10.7,
    "trade_date": "2026-02-26"
  },
  {
    "symbol": "ONC",
    "strike": 330.0,
    "expiry": "2026-08-21",
    "contracts": 100,
    "current_premium": 0.0,
    "original_premium": null,
    "trade_date": "2026-02-26"
  },
  {
    "symbol": "ORCL",
    "strike": 148.0,
    "expiry": "2026-02-27",
    "contracts": 2200,
    "current_premium": 1.4,
    "original_premium": 1.4,
    "trade_date": "2026-02-26"
  },
  {
    "symbol": "PENN",
    "strike": 11.0,
    "expiry": "2026-04-17",
    "contracts": 1200,
    "current_premium": 0.24,
    "original_premium": 0.24,
    "trade_date": "2026-02-26"
  },
  {
    "symbol": "TCOM",
    "strike": 45.0,
    "expiry": "2027-01-15",
    "contracts": 1100,
    "current_premium": 3.85,
    "original_premium": 3.85,
    "trade_date": "2026-02-26"
  },
  {
    "symbol": "TSEM",
    "strike": 85.0,
    "expiry": "2026-04-17",
    "contracts": 7800,
    "current_premium": 0.7,
    "original_premium": 0.7,
    "trade_date": "2026-02-26"
  },
  {
    "symbol": "TSM",
    "strike": 450.0,
    "expiry": "2027-01-15",
    "contracts": 2000,
    "current_premium": 107.15,
    "original_premium": 107.15,
    "trade_date": "2026-02-26"
  },
  {
    "symbol": "TTD",
    "strike": 20.0,
    "expiry": "2026-03-06",
    "contracts": 10000,
    "current_premium": 0.04,
    "original_premium": 0.04,
    "trade_date": "2026-02-26"
  },
  {
    "symbol": "UAL",
    "strike": 105.0,
    "expiry": "2026-03-20",
    "contracts": 1500,
    "current_premium": 2.02,
    "original_premium": 2.02,
    "trade_date": "2026-02-26"
  },
  {
    "symbol": "USAR",
    "strike": 17.0,
    "expiry": "2026-03-20",
    "contracts": 1500,
    "current_premium": 0.64,
    "original_premium": 0.64,
    "trade_date": "2026-02-26"
  },
  {
    "symbol": "UTHR",
    "strike": 420.0,
    "expiry": "2026-04-17",
    "contracts": 3450,
    "current_premium": 9.4,
    "original_premium": 9.4,
    "trade_date": "2026-02-26"
  },
  {
    "symbol": "VRT",
    "strike": 195.0,
    "expiry": "2026-04-02",
    "contracts": 4190,
    "current_premium": 1.59,
    "original_premium": 1.59,
    "trade_date": "2026-02-26"
  },
  {
    "symbol": "WFC",
    "strike": 79.0,
    "expiry": "2026-03-20",
    "contracts": 5000,
    "current_premium": 0.0,
    "original_premium": null,
    "trade_date": "2026-02-26"
  },
  {
    "symbol": "WMT",
    "strike": 114.0,
    "expiry": "2026-04-02",
    "contracts": 5000,
    "current_premium": 0.97,
    "original_premium": null,
    "trade_date": "2026-02-26"
  },
  {
    "symbol": "ZM",
    "strike": 70.0,
    "expiry": "2026-06-18",
    "contracts": 3000,
    "current_premium": 3.83,
    "original_premium": 3.83,
    "trade_date": "2026-02-26"
  },
  {
    "symbol": "ZM",
    "strike": 65.0,
    "expiry": "2026-09-18",
    "contracts": 5000,
    "current_premium": 3.92,
    "original_premium": 3.92,
    "trade_date": "2026-02-26"
  }
]